eye2color/__init__.py
eye2color/cli.py
eye2color/device.py
eye2color/math_utils.py
eye2color-0.1.2.dist-info/METADATA
eye2color-0.1.2.dist-info/WHEEL
eye2color-0.1.2.dist-info/entry_points.txt
eye2color-0.1.2.dist-info/top_level.txt
eye2color-0.1.2.dist-info/RECORD
