Metadata-Version: 2.1
Name: eye2color
Version: 0.1.2
Summary: CLI for Wuhan Jingce EYE2-400 Color Analyzer (MES,1)
Home-page: https://github.com/ughstudios/eye2color
Author: Your Name
Author-email: your.email@example.com
Classifier: Programming Language :: Python :: 3
Classifier: License :: OSI Approved :: MIT License
Classifier: Operating System :: OS Independent
Requires-Python: >=3.6
Requires-Dist: pyserial
Requires-Dist: numpy
